datasette_webhook_write/__init__.py
datasette_webhook_write-0.5.1.dist-info/LICENSE
datasette_webhook_write-0.5.1.dist-info/METADATA
datasette_webhook_write-0.5.1.dist-info/WHEEL
datasette_webhook_write-0.5.1.dist-info/entry_points.txt
datasette_webhook_write-0.5.1.dist-info/top_level.txt
datasette_webhook_write-0.5.1.dist-info/RECORD
