Metadata-Version: 2.2
Name: datasette-webhook-write
Version: 0.5.1
Summary: Datasette plugin to write to database via verified webhooks
Home-page: https://github.com/mfa/datasette-webhook-write
Author: Andreas Madsack
License: Apache License, Version 2.0
Project-URL: Issues, https://github.com/mfa/datasette-webhook-write/issues
Project-URL: CI, https://github.com/mfa/datasette-webhook-write/actions
Project-URL: Changelog, https://github.com/mfa/datasette-webhook-write/releases
Classifier: Development Status :: 5 - Production/Stable
Classifier: Intended Audience :: Developers
Classifier: License :: OSI Approved :: Apache Software License
Classifier: Operating System :: OS Independent
Classifier: Programming Language :: Python
Classifier: Programming Language :: Python :: 3 :: Only
Classifier: Programming Language :: Python :: 3
Classifier: Programming Language :: Python :: 3.9
Classifier: Programming Language :: Python :: 3.10
Classifier: Programming Language :: Python :: 3.11
Classifier: Programming Language :: Python :: 3.12
Classifier: Programming Language :: Python :: 3.13
Requires-Python: >=3.9.0
License-File: LICENSE
Requires-Dist: datasette
Requires-Dist: sqlite-utils
Provides-Extra: test
Requires-Dist: httpx; extra == "test"
Requires-Dist: pytest; extra == "test"
Requires-Dist: pytest-asyncio; extra == "test"
